Metadata-Version: 2.1
Name: statcord.py-beta
Version: 3.1.1
Summary: A simple API wrapper for statcord.com to connect your bot and get your bot stats.
Home-page: https://github.com/labdiscord/statcord.py/
Author: statcord.com
Keywords: statcord stat cord discordlabs discord labs bots statistics stats
Classifier: License :: OSI Approved :: MIT License
Classifier: Programming Language :: Python :: 3
Classifier: Natural Language :: English
Classifier: Intended Audience :: Developers
Classifier: Operating System :: OS Independent
Requires-Python: >= 3.5
License-File: LICENSE
Requires-Dist: aiohttp
Requires-Dist: psutil
